infoblox/__init__.py
infoblox/_helpers.py
infoblox/_settings.py
infoblox/client.py
infoblox/exceptions.py
infoblox/resource.py
infoblox/scripts/__init__.py
infoblox/scripts/client_commands.py
infoblox/scripts/options.py
infoblox/scripts/resource_commands.py
infoblox/scripts/types.py
infoblox/scripts/utils.py
infoblox/types.py
ib_client-0.1.4.dist-info/entry_points.txt
ib_client-0.1.4.dist-info/LICENSE
ib_client-0.1.4.dist-info/WHEEL
ib_client-0.1.4.dist-info/METADATA
ib_client-0.1.4.dist-info/RECORD
