Metadata-Version: 2.1
Name: ib-client
Version: 0.1.4
Summary: Infoblox client
Home-page: https://ib-client.readthedocs.io/en/stable
License: Apache-2.0
Keywords: infoblox,client,wapi,cli,api
Author: lewoudar
Author-email: lewoudar@gmail.com
Requires-Python: >=3.6,<4.0
Classifier: Environment :: Console
Classifier: Environment :: Web Environment
Classifier: Intended Audience :: Developers
Classifier: License :: OSI Approved :: Apache Software License
Classifier: Operating System :: OS Independent
Classifier: Programming Language :: Python :: 3
Classifier: Programming Language :: Python :: 3.6
Classifier: Programming Language :: Python :: 3.7
Classifier: Programming Language :: Python :: 3.8
Classifier: Topic :: Internet :: WWW/HTTP
Classifier: Topic :: Terminals
Requires-Dist: click (>=7.0,<8.0)
Requires-Dist: click-completion (>=0.5.2,<0.6.0)
Requires-Dist: click-didyoumean (>=0.0.3,<0.0.4)
Requires-Dist: pygments (>=2.5.2,<3.0.0)
Requires-Dist: python-dotenv (>=0.10.3,<0.11.0)
Requires-Dist: requests (>=2.22.0,<3.0.0)
Project-URL: Bug Tracker, https://github.com/lewoudar/ib_client/issues
Project-URL: Documentation, https://ib-client.readthedocs.io/en/stable/usage
Project-URL: Repository, https://github.com/lewoudar/ib_client
